JAAEC/JAAEC.py
JAAEC/__init__.py
JAAEC-0.1.6.dist-info/AUTHORS.rst
JAAEC-0.1.6.dist-info/LICENSE
JAAEC-0.1.6.dist-info/METADATA
JAAEC-0.1.6.dist-info/WHEEL
JAAEC-0.1.6.dist-info/top_level.txt
JAAEC-0.1.6.dist-info/RECORD
