Metadata-Version: 2.1
Name: JAAEC
Version: 0.1.6
Summary: Jake's Amazing Autoencoder is an amazing autoencoder designed for time series applications.
Home-page: https://github.com/bugsiesegal/JAAEC
Author: Jake Segal
Author-email: bugsie@segalnyc.com
License: MIT license
Keywords: JAAEC
Classifier: Development Status :: 2 - Pre-Alpha
Classifier: Intended Audience :: Developers
Classifier: License :: OSI Approved :: MIT License
Classifier: Natural Language :: English
Classifier: Programming Language :: Python :: 3
Classifier: Programming Language :: Python :: 3.6
Classifier: Programming Language :: Python :: 3.7
Classifier: Programming Language :: Python :: 3.8
Requires-Python: >=3.8
License-File: LICENSE
License-File: AUTHORS.rst
